ism/__init__.py
ism/core/__init__.py
ism/core/model.py
ism/core/stateful.py
ism/core/sub_batching.py
ism/models/__init__.py
ism/models/gru.py
ism/models/lstm.py
ism/models/rnn.py
pyism-0.0.2.dist-info/LICENSE
pyism-0.0.2.dist-info/METADATA
pyism-0.0.2.dist-info/WHEEL
pyism-0.0.2.dist-info/top_level.txt
pyism-0.0.2.dist-info/RECORD
