Metadata-Version: 2.1
Name: pyism
Version: 0.0.2
Summary: A scikit-multiflow API for Tensorflow-based models implementing Incremental Sequence Models (ISM)
Home-page: https://github.com/alvarolemos/pyism
Author: Álvaro Lemos
Author-email: alvarolemos@ufmg.br
License: UNKNOWN
Platform: UNKNOWN
Requires-Dist: numpy (==1.19.2)
Requires-Dist: scikit-multiflow (==0.5.3)
Requires-Dist: tensorflow (==2.5.0)
